mara_acl/__init__.py
mara_acl/config.py
mara_acl/keys.py
mara_acl/permissions.py
mara_acl/users.py
mara_acl/views.py
mara_acl/static/acl.css
mara_acl/static/acl.js
mara_acl/templates/acl.html
mara_acl-2.1.1.dist-info/LICENSE
mara_acl-2.1.1.dist-info/METADATA
mara_acl-2.1.1.dist-info/WHEEL
mara_acl-2.1.1.dist-info/top_level.txt
mara_acl-2.1.1.dist-info/RECORD
