Metadata-Version: 2.1
Name: mara-acl
Version: 2.1.1
Summary: Default ACL implementation for Mara
Home-page: https://github.com/mara/mara-acl
Author: Mara contributors
License: MIT
Requires-Python: >=3.6
License-File: LICENSE
Requires-Dist: mara-db (>=1.3.0)
Requires-Dist: mara-page (>=1.4.0)
